slurmdocs/__init__.py
slurmdocs/cli/__init__.py
slurmdocs/cli/cli.py
slurmdocs/cli/submodules/__init__.py
slurmdocs/cli/submodules/collect_cli.py
slurmdocs/cli/submodules/db_cli.py
slurmdocs/cli/submodules/stats_cli.py
slurmdocs/collecter/__init__.py
slurmdocs/collecter/collecter.py
slurmdocs/collecter/icollecter/__init__.py
slurmdocs/collecter/icollecter/icollecter.py
slurmdocs/collecter/icollecter/lscpu_icollecter.py
slurmdocs/collecter/icollecter/scontrol_show_node_icollecter.py
slurmdocs/database/__init__.py
slurmdocs/database/base_database.py
slurmdocs/database/slurm_cluster_database.py
slurmdocs/parse/__init__.py
slurmdocs/parse/iparse/__init__.py
slurmdocs/parse/iparse/base_iparse.py
slurmdocs/parse/iparse/ilscpu.py
slurmdocs/parse/iparse/iscontrol.py
slurmdocs/parse/parser.py
slurmdocs/session/__init__.py
slurmdocs/session/ssh_session.py
slurmdocs/statistics/__init__.py
slurmdocs/statistics/istat/__init__.py
slurmdocs/statistics/istat/gpu_specs.csv
slurmdocs/statistics/istat/istat.py
slurmdocs/statistics/istat/tflops.py
slurmdocs/statistics/stat.py
slurmdocs-1.0.0.dist-info/METADATA
slurmdocs-1.0.0.dist-info/WHEEL
slurmdocs-1.0.0.dist-info/entry_points.txt
slurmdocs-1.0.0.dist-info/RECORD
