Metadata-Version: 2.1
Name: slurmdocs
Version: 1.0.0
Summary: A simple cli tool to generate documentation for slurm
Author: hades
Author-email: nischalbhattaraipi@gmail.com
Requires-Python: >=3.10,<4.0
Classifier: Programming Language :: Python :: 3
Classifier: Programming Language :: Python :: 3.10
Classifier: Programming Language :: Python :: 3.11
Requires-Dist: click (>=8.1.7,<9.0.0)
Requires-Dist: lxml (>=4.9.3,<5.0.0)
Requires-Dist: matplotlib (>=3.8.2,<4.0.0)
Requires-Dist: pandas (>=2.1.0,<3.0.0)
Requires-Dist: paramiko (>=3.3.1,<4.0.0)
Requires-Dist: seaborn (>=0.13.0,<0.14.0)
